simple_media_sorter/Copy Files A to B.py
simple_media_sorter/Copy Files.py
simple_media_sorter/EXIF Search Move.py
simple_media_sorter/EXIF Tag Search List.py
simple_media_sorter/EXIF Tags Copier.py
simple_media_sorter/EXIF Tags Extracter.py
simple_media_sorter/EXIFadjustTime.py
simple_media_sorter/Files Compare.py
simple_media_sorter/Media Copier.py
simple_media_sorter/Search Copy.py
simple_media_sorter/config_media_sorter.py
simple_media_sorter/generate_Thumbnail_Video.py
simple_media_sorter/generate_Video_Converter.py
simple_media_sorter/getDetails.py
simple_media_sorter/moveToFolder_IMG_VID_EXIF.py
simple_media_sorter/search_Delta_Files.py
simple_media_sorter/update_EXIF_Date_fromFileName.py
simple_media_sorter/update_EXIF_Dates_fromSystemDates.py
simple_media_sorter/update_File_Name_fromEXIF.py
simple_media_sorter-1.0.150.dist-info/licenses/LICENSE
simple_media_sorter-1.0.150.dist-info/METADATA
simple_media_sorter-1.0.150.dist-info/WHEEL
simple_media_sorter-1.0.150.dist-info/top_level.txt
simple_media_sorter-1.0.150.dist-info/RECORD
