Metadata-Version: 2.4
Name: simple-media-sorter
Version: 1.0.150
Summary: A set of python modules to sort and clean media files
Author: Abdul Rahim
Author-email: a.rahim29@yahoo.com
Classifier: Programming Language :: Python :: 3
Classifier: License :: OSI Approved :: MIT License
Classifier: Operating System :: OS Independent
Requires-Python: >=3.6
License-File: LICENSE
Dynamic: author
Dynamic: author-email
Dynamic: classifier
Dynamic: description
Dynamic: description-content-type
Dynamic: license-file
Dynamic: requires-python
Dynamic: summary
